merlin/__init__.py
merlin/explain.py
merlin/merlin.py
merlin/trace.py
merlin/data/__init__.py
merlin/data/data_manager.py
merlin/data/tabular_data_manager.py
merlin/data/text_data_manager.py
merlin/surrogate/__init__.py
merlin/surrogate/generic_surrogate.py
merlin/surrogate/rulefit_surrogate.py
merlin/surrogate/sklearn_surrogate.py
merlin/util/BDD2Text.py
merlin/util/__init__.py
merlin/util/helpers.py
merlin/util/logger.py
merlinxai-0.1.2.dist-info/LICENSE
merlinxai-0.1.2.dist-info/METADATA
merlinxai-0.1.2.dist-info/WHEEL
merlinxai-0.1.2.dist-info/top_level.txt
merlinxai-0.1.2.dist-info/RECORD
