Metadata-Version: 2.1
Name: merlinxai
Version: 0.1.2
Summary: MERLIN
Home-page: https://github.com/pypa/sampleproject
Author: Andrea Seveso
Author-email: andrea.seveso@unimib.it
Project-URL: Bug Tracker, https://github.com/pypa/sampleproject/issues
Classifier: Programming Language :: Python :: 3
Classifier: License :: OSI Approved :: MIT License
Classifier: Operating System :: OS Independent
Requires-Python: >=3.6
License-File: LICENSE
Requires-Dist: pandas
Requires-Dist: pydot
Requires-Dist: scikit-learn
Requires-Dist: tqdm
Requires-Dist: stopit
Requires-Dist: graphviz
Requires-Dist: matplotlib
Requires-Dist: apyori
